pytask_parallel/__init__.py
pytask_parallel/_version.py
pytask_parallel/backends.py
pytask_parallel/build.py
pytask_parallel/config.py
pytask_parallel/execute.py
pytask_parallel/logging.py
pytask_parallel/nodes.py
pytask_parallel/plugin.py
pytask_parallel/py.typed
pytask_parallel/typing.py
pytask_parallel/utils.py
pytask_parallel/wrappers.py
pytask_parallel-0.5.1.dist-info/METADATA
pytask_parallel-0.5.1.dist-info/WHEEL
pytask_parallel-0.5.1.dist-info/entry_points.txt
pytask_parallel-0.5.1.dist-info/licenses/LICENSE
pytask_parallel-0.5.1.dist-info/RECORD
